requests_iap/__init__.py
requests_iap/iapauth.py
requests_iap-0.2.0.dist-info/METADATA
requests_iap-0.2.0.dist-info/RECORD
requests_iap-0.2.0.dist-info/WHEEL
requests_iap-0.2.0.dist-info/top_level.txt
test/__init__.py
test/test_nothing.py
