Metadata-Version: 2.1
Name: requests-iap
Version: 0.2.0
Summary: UNKNOWN
Home-page: https://github.com/kiwicom/requests-iap
Author: jan.masarik
Author-email: jan.masarik@kiwi.com
License: UNKNOWN
Platform: UNKNOWN
Classifier: Development Status :: 4 - Beta
Classifier: Environment :: Console
Classifier: Operating System :: OS Independent
Classifier: Programming Language :: Python :: 2
Classifier: Programming Language :: Python :: 3
Requires-Dist: pyjwt
Requires-Dist: requests
Requires-Dist: cryptography
